promptzl/__init__.py
promptzl/modules.py
promptzl/prompt.py
promptzl/utils.py
promptzl-1.0.0.dist-info/LICENSE.md
promptzl-1.0.0.dist-info/METADATA
promptzl-1.0.0.dist-info/WHEEL
promptzl-1.0.0.dist-info/top_level.txt
promptzl-1.0.0.dist-info/RECORD
