Metadata-Version: 2.1
Name: promptzl
Version: 1.0.0
Summary: Promptzl - LLMs as Classifiers
Author-email: Philipp Koch <PhillKoch@protonmail.com>
Project-URL: homepage, https://promptzl.readthedocs.io/en/latest/
Project-URL: Repository, https://github.com/LazerLambda/Promptzl
Project-URL: Issues, https://github.com/LazerLambda/Promptzl/issues
Keywords: llm,nlp,transformers,classifiers,predictive modeling,machine learning,torch,huggingface,zero-shot,prompting
Classifier: Development Status :: 5 - Production/Stable
Classifier: Intended Audience :: Developers
Classifier: Intended Audience :: Science/Research
Classifier: Intended Audience :: Information Technology
Classifier: Intended Audience :: Legal Industry
Classifier: Intended Audience :: Financial and Insurance Industry
Classifier: License :: OSI Approved :: Apache Software License
Classifier: Operating System :: OS Independent
Classifier: Programming Language :: Python :: 3.9
Classifier: Programming Language :: Python :: 3.10
Classifier: Programming Language :: Python :: 3.11
Classifier: Programming Language :: Python :: 3.12
Classifier: Programming Language :: Python :: 3.13
Requires-Python: >=3.9
License-File: LICENSE.md
Requires-Dist: datasets
Requires-Dist: numpy<2.0.0
Requires-Dist: pandas
Requires-Dist: polars
Requires-Dist: sentencepiece
Requires-Dist: torch>=2.0.0
Requires-Dist: tqdm
Requires-Dist: transformers>=4.0.0
